LICENSE
MANIFEST.in
Makefile
README.md
pyproject.toml
setup.py
pyqrack/__init__.py
pyqrack/neuron_activation_fn.py
pyqrack/pauli.py
pyqrack/qrack_ace_backend.py
pyqrack/qrack_circuit.py
pyqrack/qrack_neuron.py
pyqrack/qrack_neuron_torch_layer.py
pyqrack/qrack_simulator.py
pyqrack/qrack_stabilizer.py
pyqrack/quimb_circuit_type.py
pyqrack/qrack_system/__init__.py
pyqrack/qrack_system/qrack_system.py
pyqrack/stats/__init__.py
pyqrack/stats/load_quantized_data.py
pyqrack/stats/quantize_by_range.py
pyqrack_cuda_complex128.egg-info/PKG-INFO
pyqrack_cuda_complex128.egg-info/SOURCES.txt
pyqrack_cuda_complex128.egg-info/dependency_links.txt
pyqrack_cuda_complex128.egg-info/not-zip-safe
pyqrack_cuda_complex128.egg-info/requires.txt
pyqrack_cuda_complex128.egg-info/top_level.txt